setup.py
devopsprecheck/__init__.py
devopsprecheck/main.py
devopsprecheck/network_helper.py
devopsprecheck/package_helper.py
devopsprecheck/paramater_helper.py
devopsprecheck/systeminfo_helper.py
devopsprecheck.egg-info/PKG-INFO
devopsprecheck.egg-info/SOURCES.txt
devopsprecheck.egg-info/dependency_links.txt
devopsprecheck.egg-info/entry_points.txt
devopsprecheck.egg-info/pbr.json
devopsprecheck.egg-info/requires.txt
devopsprecheck.egg-info/top_level.txt