Metadata-Version: 1.1
Name: devopsprecheck
Version: 0.0.2
Summary: Python precheck package for DevOps purpose
Home-page: https://github.com/DennyZhang/devopsprecheck
Author: DennyZhang
Author-email: contact@denyzhang.com
License: Apache2
Platform: UNKNOWN
Classifier: Development Status :: 5 - Production/Stable
Classifier: Intended Audience :: Developers
Classifier: License :: OSI Approved :: Apache Software License
Classifier: Programming Language :: Python
